MANIFEST.in
README.md
requirements.txt
setup.cfg
setup.py
napalm_ansible/__init__.py
napalm_ansible.egg-info/PKG-INFO
napalm_ansible.egg-info/SOURCES.txt
napalm_ansible.egg-info/dependency_links.txt
napalm_ansible.egg-info/entry_points.txt
napalm_ansible.egg-info/requires.txt
napalm_ansible.egg-info/top_level.txt
napalm_ansible/modules/__init__.py
napalm_ansible/modules/napalm_cli.py
napalm_ansible/modules/napalm_diff_yang.py
napalm_ansible/modules/napalm_get_facts.py
napalm_ansible/modules/napalm_install_config.py
napalm_ansible/modules/napalm_parse_yang.py
napalm_ansible/modules/napalm_ping.py
napalm_ansible/modules/napalm_translate_yang.py
napalm_ansible/modules/napalm_validate.py
napalm_ansible/plugins/__init__.py
napalm_ansible/plugins/action/__init__.py
napalm_ansible/plugins/action/napalm.py
napalm_ansible/plugins/action/napalm_get_facts.py
napalm_ansible/plugins/action/napalm_install_config.py
napalm_ansible/plugins/action/napalm_parse_yang.py
napalm_ansible/plugins/action/napalm_ping.py
napalm_ansible/plugins/action/napalm_validate.py