Metadata-Version: 1.1
Name: napalm-ansible
Version: 1.0.0
Summary: Network Automation and Programmability Abstraction Layer with Multivendor support
Home-page: https://github.com/napalm-automation/napalm-ansible
Author: David Barroso, Kirk Byers, Mircea Ulinic
Author-email: dbarrosop@dravetech.com, ktbyers@twb-tech.com
License: UNKNOWN
Platform: UNKNOWN
Classifier: Topic :: Utilities
Classifier: Programming Language :: Python
Classifier: Programming Language :: Python :: 2
Classifier: Programming Language :: Python :: 2.7
Classifier: Programming Language :: Python :: 3
Classifier: Programming Language :: Python :: 3.5
Classifier: Programming Language :: Python :: 3.6
Classifier: Operating System :: POSIX :: Linux
Classifier: Operating System :: POSIX :: Linux
Classifier: Operating System :: MacOS
